weathercls/__init__.py
weathercls/weatherapicom/forecast_weather/Alerts.py
weathercls/weatherapicom/forecast_weather/AlertsAlert.py
weathercls/weatherapicom/forecast_weather/Current.py
weathercls/weatherapicom/forecast_weather/CurrentAirQuality.py
weathercls/weatherapicom/forecast_weather/CurrentCondition.py
weathercls/weatherapicom/forecast_weather/Forecast.py
weathercls/weatherapicom/forecast_weather/ForecastAstro.py
weathercls/weatherapicom/forecast_weather/ForecastCondition.py
weathercls/weatherapicom/forecast_weather/ForecastDay.py
weathercls/weatherapicom/forecast_weather/ForecastDayCondition.py
weathercls/weatherapicom/forecast_weather/ForecastForecastday.py
weathercls/weatherapicom/forecast_weather/ForecastHour.py
weathercls/weatherapicom/forecast_weather/ForecastWeather.py
weathercls/weatherapicom/forecast_weather/Location.py
weathercls-1.0.0.dist-info/LICENSE
weathercls-1.0.0.dist-info/METADATA
weathercls-1.0.0.dist-info/WHEEL
weathercls-1.0.0.dist-info/RECORD
